sigmoidalvision/__init__.py
sigmoidalvision/assets/__init__.py
sigmoidalvision/assets/catalog.py
sigmoidalvision/assets/downloader.py
sigmoidalvision-0.1.0.dist-info/LICENSE
sigmoidalvision-0.1.0.dist-info/METADATA
sigmoidalvision-0.1.0.dist-info/WHEEL
sigmoidalvision-0.1.0.dist-info/RECORD
